easy_password_generator.py
password_generator/__init__.py
password_generator/easy_password_generator.py
password_generator/test.py
easy_password_generator-0.0.7.dist-info/LICENSE
easy_password_generator-0.0.7.dist-info/METADATA
easy_password_generator-0.0.7.dist-info/WHEEL
easy_password_generator-0.0.7.dist-info/top_level.txt
easy_password_generator-0.0.7.dist-info/RECORD
