Metadata-Version: 2.1
Name: easy-password-generator
Version: 0.0.7
Summary: A powerful but simple to use strong password generation library
Home-page: https://github.com/soniaghongadi/password-generator
Author: Sonia Ghongadi
Author-email: author@example.com
License: UNKNOWN
Platform: UNKNOWN
Classifier: Programming Language :: Python :: 3
Classifier: License :: OSI Approved :: MIT License
Classifier: Operating System :: OS Independent
Requires-Python: >=3.6
